docassemble/base/DA.py
docassemble/base/__init__.py
docassemble/base/actions.py
docassemble/base/amazon.py
docassemble/base/astparser.py
docassemble/base/bates.py
docassemble/base/config.py
docassemble/base/core.py
docassemble/base/error.py
docassemble/base/file_docx.py
docassemble/base/filter.py
docassemble/base/functions.py
docassemble/base/generate_key.py
docassemble/base/geocode.py
docassemble/base/interview_cache.py
docassemble/base/legal.py
docassemble/base/logger.py
docassemble/base/mermaid.py
docassemble/base/microsoft.py
docassemble/base/pandoc.py
docassemble/base/parse.py
docassemble/base/pdfa.py
docassemble/base/pdftk.py
docassemble/base/read_config.py
docassemble/base/save_status.py
docassemble/base/sql.py
docassemble/base/standardformatter.py
docassemble/base/test.py
docassemble/base/util.py
docassemble/base/data/macros/Module1.xba
docassemble/base/data/questions/basic-questions.yml
docassemble/base/data/questions/default-interview.yml
docassemble/base/data/questions/docstring.yml
docassemble/base/data/questions/documentation.yml
docassemble/base/data/questions/example-list.yml
docassemble/base/data/questions/pgcodecache.yml
docassemble/base/data/questions/title_documentation.yml
docassemble/base/data/questions/examples/action-button-html.yml
docassemble/base/data/questions/examples/action-buttons-before.yml
docassemble/base/data/questions/examples/action-buttons-code.yml
docassemble/base/data/questions/examples/action-buttons-http.yml
docassemble/base/data/questions/examples/action-buttons.yml
docassemble/base/data/questions/examples/actions-demo.yml
docassemble/base/data/questions/examples/actions-parameters.yml
docassemble/base/data/questions/examples/actions.yml
docassemble/base/data/questions/examples/add-separators.yml
docassemble/base/data/questions/examples/address-autocomplete-cities.yml
docassemble/base/data/questions/examples/address-autocomplete-establishment.yml
docassemble/base/data/questions/examples/address-autocomplete-nz.yml
docassemble_base-1.9.0.dist-info/licenses/LICENSE.txt
docassemble_base-1.9.0.dist-info/METADATA
docassemble_base-1.9.0.dist-info/WHEEL
docassemble_base-1.9.0.dist-info/top_level.txt
docassemble_base-1.9.0.dist-info/RECORD
